mo_math/__init__.py
mo_math/aes_crypto.py
mo_math/crypto.py
mo_math/hashes.py
mo_math/randoms.py
mo_math/rsa_crypto.py
mo_math/stats.py
mo_math/vendor/__init__.py
mo_math/vendor/aespython/__init__.py
mo_math/vendor/aespython/aes_cipher.py
mo_math/vendor/aespython/aes_tables.py
mo_math/vendor/aespython/cbc_mode.py
mo_math/vendor/aespython/cfb_mode.py
mo_math/vendor/aespython/cipher_mode.py
mo_math/vendor/aespython/key_expander.py
mo_math/vendor/aespython/mode_test.py
mo_math/vendor/aespython/ofb_mode.py
mo_math/vendor/aespython/test_keys.py
mo_math/vendor/strangman/__init__.py
mo_math/vendor/strangman/pstat.py
mo_math/vendor/strangman/stats.py
mo_math/vendor/strangman/statstest.py
mo_math-7.685.25166.dist-info/licenses/LICENSE
mo_math-7.685.25166.dist-info/METADATA
mo_math-7.685.25166.dist-info/WHEEL
mo_math-7.685.25166.dist-info/top_level.txt
mo_math-7.685.25166.dist-info/RECORD
